tcrutils/__init__.py
tcrutils/_version.py
tcrutils/aevents.py
tcrutils/b64.py
tcrutils/case.py
tcrutils/class_.py
tcrutils/classfuncs.py
tcrutils/codeblock.py
tcrutils/compare.py
tcrutils/console.py
tcrutils/context.py
tcrutils/decorator.py
tcrutils/dev.py
tcrutils/dict.py
tcrutils/dir.py
tcrutils/discord_ifys.py
tcrutils/ensure_deps.py
tcrutils/execute.py
tcrutils/extract_error.py
tcrutils/getch.py
tcrutils/import_.py
tcrutils/inject.py
tcrutils/input.py
tcrutils/inspect.py
tcrutils/int.py
tcrutils/iterable.py
tcrutils/joke.py
tcrutils/lang.py
tcrutils/language.py
tcrutils/misspellings.py
tcrutils/path.py
tcrutils/print.py
tcrutils/regex.py
tcrutils/result.py
tcrutils/rich.py
tcrutils/run.py
tcrutils/sdb.py
tcrutils/sdb2.py
tcrutils/string.py
tcrutils/temp.py
tcrutils/terminal.py
tcrutils/test_.py
tcrutils/timestr.py
tcrutils/timestr2.py
tcrutils/tree.py
tcrutils/typehints.py
tcrutils/types.py
tcrutils/uptime.py
tcrutils/void.py
tcrutils/repl/__init__.py
tcrutils/repl/nodes.py
tcrutils/repl/parser.py
tcrutils/repl/repl.py
tcrutils-13.1.39.dist-info/METADATA
tcrutils-13.1.39.dist-info/WHEEL
tcrutils-13.1.39.dist-info/licenses/LICENSE
tcrutils-13.1.39.dist-info/RECORD
