Metadata-Version: 2.4
Name: tcrutils
Version: 13.1.39
Summary: Useful stuff for TCR projects!
Project-URL: Documentation, https://xkcd.com/730/
Project-URL: Source (GitHub), https://github.com/anamoyee/tcrutils
Author: anamoyee
Maintainer: anamoyee
License: GPL-3.0
License-File: LICENSE
Classifier: Development Status :: 4 - Beta
Classifier: Intended Audience :: Developers
Classifier: Operating System :: MacOS
Classifier: Operating System :: Microsoft :: MS-DOS
Classifier: Operating System :: Microsoft :: Windows
Classifier: Operating System :: POSIX
Classifier: Operating System :: POSIX :: Linux
Classifier: Programming Language :: Python :: 3 :: Only
Classifier: Programming Language :: Python :: 3.13
Classifier: Topic :: Utilities
Classifier: Typing :: Typed
Requires-Python: >=3.12
Requires-Dist: colored>=2.3.0
Requires-Dist: pytz>=2018.5
